IncSVD/EvolvingMatrix.py
IncSVD-0.2.7.dist-info/LICENSE
IncSVD-0.2.7.dist-info/METADATA
IncSVD-0.2.7.dist-info/WHEEL
IncSVD-0.2.7.dist-info/top_level.txt
IncSVD-0.2.7.dist-info/RECORD
