Metadata-Version: 2.2
Name: IncSVD
Version: 0.2.7
Summary: Towards Efficient Updating of Truncated Singular Value Decompostion
Author-email: Haoran Deng <denghaoran@zju.edu.cn>
Project-URL: Homepage, https://github.com/HaoranDeng/IncSVD
Project-URL: Bug Tracker, https://github.com/HaoranDeng/IncSVD/issues
Classifier: Programming Language :: Python :: 3
Classifier: License :: OSI Approved :: MIT License
Classifier: Operating System :: OS Independent
Requires-Python: >=3.6
License-File: LICENSE
Requires-Dist: numpy>=1.19
Requires-Dist: scikit-learn>=0.23
Requires-Dist: scipy>=1.5
